logddd/__init__.py
logddd/main.py
logddd-0.13.3.dist-info/LICENSE
logddd-0.13.3.dist-info/METADATA
logddd-0.13.3.dist-info/WHEEL
logddd-0.13.3.dist-info/top_level.txt
logddd-0.13.3.dist-info/RECORD
