Metadata-Version: 2.1
Name: logddd
Version: 0.13.3
Summary: print python logddd
Home-page: https://github.com/dailinfeng66/py-simple-log
Author: LinFeng Dai
Author-email: dailinfeng66@163.com
License: UNKNOWN
Platform: UNKNOWN
Classifier: Programming Language :: Python :: 3
Classifier: License :: OSI Approved :: MIT License
Classifier: Operating System :: OS Independent
